gmx_python_sdk/__init__.py
gmx_python_sdk/data_store/placeholder.txt
gmx_python_sdk/scripts/__init__.py
gmx_python_sdk/scripts/v2/__init__.py
gmx_python_sdk/scripts/v2/approve_token_for_spend.py
gmx_python_sdk/scripts/v2/gas_utils.py
gmx_python_sdk/scripts/v2/get/get.py
gmx_python_sdk/scripts/v2/get/get_available_liquidity.py
gmx_python_sdk/scripts/v2/get/get_borrow_apr.py
gmx_python_sdk/scripts/v2/get/get_claimable_fees.py
gmx_python_sdk/scripts/v2/get/get_contract_balance.py
gmx_python_sdk/scripts/v2/get/get_funding_apr.py
gmx_python_sdk/scripts/v2/get/get_glv_stats.py
gmx_python_sdk/scripts/v2/get/get_gm_prices.py
gmx_python_sdk/scripts/v2/get/get_markets.py
gmx_python_sdk/scripts/v2/get/get_open_interest.py
gmx_python_sdk/scripts/v2/get/get_open_positions.py
gmx_python_sdk/scripts/v2/get/get_oracle_prices.py
gmx_python_sdk/scripts/v2/get/get_pool_tvl.py
gmx_python_sdk/scripts/v2/get/test.py
gmx_python_sdk/scripts/v2/gmx_utils.py
gmx_python_sdk/scripts/v2/keys.py
gmx_python_sdk/scripts/v2/order/create_decrease_order.py
gmx_python_sdk/scripts/v2/order/create_deposit_order.py
gmx_python_sdk/scripts/v2/order/create_increase_order.py
gmx_python_sdk/scripts/v2/order/create_swap_order.py
gmx_python_sdk/scripts/v2/order/create_withdrawal_order.py
gmx_python_sdk/scripts/v2/order/deposit.py
gmx_python_sdk/scripts/v2/order/liquidity_argument_parser.py
gmx_python_sdk/scripts/v2/order/order.py
gmx_python_sdk/scripts/v2/order/order_argument_parser.py
gmx_python_sdk/scripts/v2/order/withdraw.py
gmx_python_sdk-0.0.11.dist-info/LICENSE
gmx_python_sdk-0.0.11.dist-info/METADATA
gmx_python_sdk-0.0.11.dist-info/WHEEL
gmx_python_sdk-0.0.11.dist-info/RECORD
