Metadata-Version: 2.3
Name: gmx_python_sdk
Version: 0.0.11
Summary: A python based SDK developed for interacting with GMX v2
License: MIT
Author: snipermonke01
Author-email: snipermonke01@proton.me
Maintainer: snipermonke01
Maintainer-email: snipermonke01@proton.me
Requires-Python: >=3.10.4
Classifier: License :: OSI Approved :: MIT License
Classifier: Programming Language :: Python :: 3
Classifier: Programming Language :: Python :: 3.11
Classifier: Programming Language :: Python :: 3.12
Classifier: Programming Language :: Python :: 3.13
Requires-Dist: Packaging (>=24.1)
Requires-Dist: hexbytes (>=0.3.1)
Requires-Dist: numerize (>=0.12)
Requires-Dist: numpy (>=1.26.3)
Requires-Dist: pandas (>=1.4.2)
Requires-Dist: pyyaml (>=6.0.1)
Requires-Dist: web3 (>=6.10.0)
Project-URL: Repository, https://github.com/snipermonke01/gmx_python_sdk
